google_api_utils/__init__.py
google_api_utils/Google.py
google_api_utils-0.6.0.dist-info/WHEEL
google_api_utils-0.6.0.dist-info/METADATA
google_api_utils-0.6.0.dist-info/RECORD
